LICENSE
mpxl2csv/__init__.py
mpxl2csv/mpxl2csv.py
mpxl2csv-0.2.0.dist-info/LICENSE
mpxl2csv-0.2.0.dist-info/METADATA
mpxl2csv-0.2.0.dist-info/WHEEL
mpxl2csv-0.2.0.dist-info/RECORD
